README.md
setup.py
cqe_jdsu.egg-info/PKG-INFO
cqe_jdsu.egg-info/SOURCES.txt
cqe_jdsu.egg-info/dependency_links.txt
cqe_jdsu.egg-info/not-zip-safe
cqe_jdsu.egg-info/top_level.txt
jdsu/__init__.py
jdsu/phys_layer.py