Metadata-Version: 1.0
Name: cqe-jdsu
Version: 0.2
Summary: package required for JDSU API
Home-page: https://github.com/cafylib/cqe-jdsu
Author: Deepesh Kaushal
Author-email: kaushal_deepesh@yahoo.in
License: VIAVI
Platform: UNKNOWN
